satnogsconfig/__init__.py
satnogsconfig/__main__.py
satnogsconfig/_version.py
satnogsconfig/config.py
satnogsconfig/menu.py
satnogsconfig/menu.yml
satnogsconfig/settings.py
satnogsconfig/helpers/__init__.py
satnogsconfig/helpers/satnogssetup.py
satnogsconfig/helpers/support.py
satnogs_config-1.0.dist-info/LICENSE
satnogs_config-1.0.dist-info/METADATA
satnogs_config-1.0.dist-info/WHEEL
satnogs_config-1.0.dist-info/entry_points.txt
satnogs_config-1.0.dist-info/top_level.txt
satnogs_config-1.0.dist-info/RECORD
